bd/postal_code.py
bd/__init__.py
bd/divisions.py
bd/districts.py
bd/thana.py
BD-0.0.5.dist-info/DESCRIPTION.rst
BD-0.0.5.dist-info/METADATA
BD-0.0.5.dist-info/RECORD
BD-0.0.5.dist-info/WHEEL
BD-0.0.5.dist-info/top_level.txt
BD-0.0.5.dist-info/metadata.json
