Metadata-Version: 1.0
Name: BD
Version: 0.0.5
Summary: Bangladesh Details with postal code
Home-page: https://vimmaniac.com/
Author: Ahsan Habib
Author-email: ahsan@vimmaniac.com
License: MIT
Keywords: BD,Bangladesh,Postal-Code,zip-code,District,Division,Thana
Platform: UNKNOWN
